WuyunZhishikuDierBufen/README.md
WuyunZhishikuDierBufen/__init__.py
WuyunZhishikuDierBufen/__main__.py
WuyunZhishikuDierBufen/file.epub
WuyunZhishikuDierBufen/index.html
WuyunZhishikuDierBufen/css/__init__.py
WuyunZhishikuDierBufen/css/annotations.css
WuyunZhishikuDierBufen/css/main.css
WuyunZhishikuDierBufen/css/normalize.css
WuyunZhishikuDierBufen/css/popup.css
WuyunZhishikuDierBufen/font/__init__.py
WuyunZhishikuDierBufen/font/fontello.eot
WuyunZhishikuDierBufen/font/fontello.svg
WuyunZhishikuDierBufen/font/fontello.ttf
WuyunZhishikuDierBufen/font/fontello.woff
WuyunZhishikuDierBufen/img/__init__.py
WuyunZhishikuDierBufen/img/annotator-glyph-sprite.png
WuyunZhishikuDierBufen/img/annotator-icon-sprite.png
WuyunZhishikuDierBufen/img/apple-touch-icon.png
WuyunZhishikuDierBufen/img/cancelfullscreen.png
WuyunZhishikuDierBufen/img/close.png
WuyunZhishikuDierBufen/img/fullscreen.png
WuyunZhishikuDierBufen/img/loader.gif
WuyunZhishikuDierBufen/img/menu-icon.png
WuyunZhishikuDierBufen/img/save.png
WuyunZhishikuDierBufen/img/saved.png
WuyunZhishikuDierBufen/img/settings-s.png
WuyunZhishikuDierBufen/img/settings.png
WuyunZhishikuDierBufen/img/star.png
WuyunZhishikuDierBufen/js/__init__.py
WuyunZhishikuDierBufen/js/epub.js
WuyunZhishikuDierBufen/js/epub.min.js
WuyunZhishikuDierBufen/js/epub.min.map
WuyunZhishikuDierBufen/js/hooks.min.js
WuyunZhishikuDierBufen/js/hooks.min.map
WuyunZhishikuDierBufen/js/reader.js
WuyunZhishikuDierBufen/js/reader.js.map
WuyunZhishikuDierBufen/js/reader.min.js
WuyunZhishikuDierBufen/js/reader.min.map
WuyunZhishikuDierBufen/js/hooks/__init__.py
WuyunZhishikuDierBufen/js/hooks/extensions/__init__.py
WuyunZhishikuDierBufen/js/hooks/extensions/highlight.js
WuyunZhishikuDierBufen/js/libs/__init__.py
WuyunZhishikuDierBufen/js/libs/jquery.min.js
WuyunZhishikuDierBufen/js/libs/localforage.min.js
WuyunZhishikuDierBufen/js/libs/screenfull.js
WuyunZhishikuDierBufen/js/libs/screenfull.min.js
WuyunZhishikuDierBufen/js/libs/zip.min.js
wuyun_zhishiku_dier_bufen-2024.3.5.0.dist-info/METADATA
wuyun_zhishiku_dier_bufen-2024.3.5.0.dist-info/WHEEL
wuyun_zhishiku_dier_bufen-2024.3.5.0.dist-info/entry_points.txt
wuyun_zhishiku_dier_bufen-2024.3.5.0.dist-info/top_level.txt
wuyun_zhishiku_dier_bufen-2024.3.5.0.dist-info/RECORD
